gsheet/__init__.py
gsheet/gsheet.py
gsheet_alpa-0.0.10.dist-info/LICENSE
gsheet_alpa-0.0.10.dist-info/METADATA
gsheet_alpa-0.0.10.dist-info/WHEEL
gsheet_alpa-0.0.10.dist-info/top_level.txt
gsheet_alpa-0.0.10.dist-info/RECORD
