Metadata-Version: 2.1
Name: gsheet-alpa
Version: 0.0.10
Summary: Package for working with Google Sheet
Home-page: https://bitbucket.org/alpaalpa/gsheet/
Author: Albert Pang
Author-email: alpaaccount@mac.com
License: UNKNOWN
Platform: UNKNOWN
Classifier: Programming Language :: Python :: 3
Classifier: License :: OSI Approved :: MIT License
Classifier: Operating System :: OS Independent
Requires-Python: >=3.6
Requires-Dist: gspread
Requires-Dist: gspread-dataframe
Requires-Dist: numpy
Requires-Dist: oauth2client
Requires-Dist: pandas
